airflow/providers/fernet_secrets/__init__.py
airflow/providers/fernet_secrets/get_provider_info.py
airflow/providers/fernet_secrets/py.typed
airflow/providers/fernet_secrets/decorators/__init__.py
airflow/providers/fernet_secrets/decorators/sync.py
airflow/providers/fernet_secrets/operators/__init__.py
airflow/providers/fernet_secrets/operators/sync.py
airflow/providers/fernet_secrets/secrets/__init__.py
airflow/providers/fernet_secrets/secrets/secret_manager.py
airflow_fernet_secrets/__init__.py
airflow_fernet_secrets/_typeshed.py
airflow_fernet_secrets/const.py
airflow_fernet_secrets/dynamic.py
airflow_fernet_secrets/exceptions.py
airflow_fernet_secrets/info.py
airflow_fernet_secrets/info.yaml
airflow_fernet_secrets/py.typed
airflow_fernet_secrets/typings.py
airflow_fernet_secrets/config/__init__.py
airflow_fernet_secrets/config/client.py
airflow_fernet_secrets/config/common.py
airflow_fernet_secrets/config/server.py
airflow_fernet_secrets/connection/__init__.py
airflow_fernet_secrets/connection/client.py
airflow_fernet_secrets/connection/common.py
airflow_fernet_secrets/connection/server.py
airflow_fernet_secrets/connection/dump/__init__.py
airflow_fernet_secrets/connection/dump/main.py
airflow_fernet_secrets/connection/dump/mssql.py
airflow_fernet_secrets/connection/dump/odbc.py
airflow_fernet_secrets/connection/dump/postgresql.py
airflow_fernet_secrets/connection/dump/sqlite.py
airflow_fernet_secrets/connection/json/__init__.py
airflow_fernet_secrets/connection/json/class_to_tuple.py
airflow_fernet_secrets/database/__init__.py
airflow_fernet_secrets/database/connect.py
airflow_fernet_secrets/database/model.py
airflow_fernet_secrets/database/revision/__init__.py
airflow_fernet_secrets/database/revision/init.py
airflow_fernet_secrets/decorators/__init__.py
airflow_fernet_secrets/decorators/base.py
airflow_fernet_secrets/decorators/dump.py
airflow_fernet_secrets/decorators/load.py
airflow_fernet_secrets/log/__init__.py
airflow_fernet_secrets/log/client.py
airflow_fernet_secrets-0.2.1.dist-info/METADATA
airflow_fernet_secrets-0.2.1.dist-info/WHEEL
airflow_fernet_secrets-0.2.1.dist-info/entry_points.txt
airflow_fernet_secrets-0.2.1.dist-info/licenses/LICENSE
airflow_fernet_secrets-0.2.1.dist-info/RECORD
