Metadata-Version: 2.3
Name: airflow-fernet-secrets
Version: 0.2.1
Summary: airflow filesystem secret backend using fernet
Project-URL: Repository, https://github.com/phi-friday/airflow-fernet-secrets
Author-email: phi <phi.friday@gmail.com>
License:                                  Apache License
License-File: LICENSE
Classifier: Development Status :: 4 - Beta
Classifier: Framework :: Apache Airflow
Classifier: License :: OSI Approved :: Apache Software License
Classifier: Programming Language :: Python :: 3.8
Classifier: Programming Language :: Python :: 3.9
Classifier: Programming Language :: Python :: 3.10
Classifier: Programming Language :: Python :: 3.11
Classifier: Programming Language :: Python :: 3.12
Classifier: Programming Language :: Python :: 3.13
Requires-Python: <3.14,>=3.8
Requires-Dist: cryptography
Requires-Dist: filelock>=3.15
Requires-Dist: jsonschema
Requires-Dist: pyyaml
Requires-Dist: sqlalchemy>=1.4
Requires-Dist: typing-extensions>=4.4.0
Provides-Extra: asyncio
Requires-Dist: aiosqlite; extra == 'asyncio'
Requires-Dist: sqlalchemy[asyncio]>=1.4; extra == 'asyncio'
Provides-Extra: test
Requires-Dist: anyio; extra == 'test'
Requires-Dist: apache-airflow>=2.9.3; (python_version != '3.13') and extra == 'test'
Requires-Dist: psycopg2>=2; extra == 'test'
Requires-Dist: pymssql>=2; extra == 'test'
Requires-Dist: pyodbc>=5.1; extra == 'test'
Requires-Dist: pytest-xdist>=3.5.0; extra == 'test'
Requires-Dist: pytest>=7; extra == 'test'
Requires-Dist: uvloop; (platform_system != 'Windows') and extra == 'test'
